aws_sdk_polars/__init__.py
aws_sdk_polars/_version.py
aws_sdk_polars/api.py
aws_sdk_polars/boto_ses.py
aws_sdk_polars/constants.py
aws_sdk_polars/paths.py
aws_sdk_polars/typehint.py
aws_sdk_polars/utils.py
aws_sdk_polars/docs/__init__.py
aws_sdk_polars/s3/__init__.py
aws_sdk_polars/s3/_partition.py
aws_sdk_polars/s3/api.py
aws_sdk_polars/s3/partition.py
aws_sdk_polars/s3/read.py
aws_sdk_polars/s3/write.py
aws_sdk_polars/tests/__init__.py
aws_sdk_polars/tests/helper.py
aws_sdk_polars/tests/mock_aws.py
aws_sdk_polars/vendor/__init__.py
aws_sdk_polars/vendor/better_enum.py
aws_sdk_polars/vendor/pytest_cov_helper.py
aws_sdk_polars-0.1.4.dist-info/AUTHORS.rst
aws_sdk_polars-0.1.4.dist-info/LICENSE.txt
aws_sdk_polars-0.1.4.dist-info/METADATA
aws_sdk_polars-0.1.4.dist-info/WHEEL
aws_sdk_polars-0.1.4.dist-info/top_level.txt
aws_sdk_polars-0.1.4.dist-info/RECORD
