Metadata-Version: 2.1
Name: aws_sdk_polars
Version: 0.1.4
Summary: An open-source Python initiative that harnesses the lightning-fast capabilities of the Polars library within the AWS ecosystem. 
Home-page: https://github.com/MacHu-GWU/aws_sdk_polars-project
Download-URL: https://pypi.python.org/pypi/aws_sdk_polars/0.1.4#downloads
Author: Sanhe Hu
Author-email: husanhe@gmail.com
Maintainer: Sanhe Hu
Maintainer-email: husanhe@email.com
License: MIT
Platform: Windows
Platform: MacOS
Platform: Unix
Classifier: Development Status :: 4 - Beta
Classifier: Intended Audience :: Developers
Classifier: License :: OSI Approved :: MIT License
Classifier: Natural Language :: English
Classifier: Operating System :: Microsoft :: Windows
Classifier: Operating System :: MacOS
Classifier: Operating System :: Unix
Classifier: Programming Language :: Python
Classifier: Programming Language :: Python :: 3.8
Classifier: Programming Language :: Python :: 3.9
Classifier: Programming Language :: Python :: 3.10
Classifier: Programming Language :: Python :: 3.11
Classifier: Programming Language :: Python :: 3.12
Classifier: Programming Language :: Python :: 3 :: Only
Requires-Python: >=3.8
License-File: LICENSE.txt
License-File: AUTHORS.rst
Requires-Dist: boto-session-manager <2.0.0,>=1.7.2
Requires-Dist: s3pathlib <3.0.0,>=2.3.1
Requires-Dist: polars <2.0.0,>=1.5.0
Requires-Dist: polars-writer <1.0.0,>=0.3.2
Requires-Dist: aws-glue-catalog <1.0.0,>=0.1.1
Requires-Dist: more-itertools <11.0.0,>=10.5.0
Requires-Dist: compress <1.0.0,>=0.1.1
Requires-Dist: typing-extensions <5.0.0,>=4.4.0
Requires-Dist: tabulate <1.0.0,>=0.9.0
Provides-Extra: docs
Requires-Dist: Sphinx ==5.3.0 ; extra == 'docs'
Requires-Dist: sphinx-jinja ==2.0.2 ; extra == 'docs'
Requires-Dist: sphinx-copybutton ==0.5.1 ; extra == 'docs'
Requires-Dist: sphinx-design ==0.5.0 ; extra == 'docs'
Requires-Dist: furo ==2023.03.27 ; extra == 'docs'
Requires-Dist: nbsphinx ==0.8.12 ; extra == 'docs'
Requires-Dist: rstobj ==1.2.1 ; extra == 'docs'
Requires-Dist: pygments ==2.15.1 ; extra == 'docs'
Requires-Dist: ipython ==8.10.0 ; extra == 'docs'
Requires-Dist: docfly ==2.0.3 ; extra == 'docs'
Provides-Extra: tests
Requires-Dist: pytest ; extra == 'tests'
Requires-Dist: pytest-cov ; extra == 'tests'
Requires-Dist: moto <6.0.0,>=5.0.0 ; extra == 'tests'
